valorant/__init__.py
valorant/base.py
valorant/config.py
valorant/version.py
valorant/utils/__init__.py
valorant/utils/agent.py
valorant/utils/communication.py
valorant/utils/gameplay.py
valorant/utils/helper.py
valorant/utils/keybind.py
valorant/utils/market.py
valorant/utils/preprocessing.py
valorant/utils/record.py
pyvalo-0.2.2.dist-info/LICENSE.txt
pyvalo-0.2.2.dist-info/METADATA
pyvalo-0.2.2.dist-info/WHEEL
pyvalo-0.2.2.dist-info/top_level.txt
pyvalo-0.2.2.dist-info/RECORD
