Metadata-Version: 2.1
Name: pyvalo
Version: 0.2.2
Summary: Unofficial Valorant Tools Library to Create Assistant Bot
Home-page: https://github.com/vnpnh/Pyvalo
Author: vnpnh
Author-email: no@email.com
License: MIT
Keywords: valorant tools
Platform: UNKNOWN
Classifier: License :: OSI Approved :: MIT License
Classifier: Operating System :: OS Independent
Classifier: Programming Language :: Python :: 3
Classifier: Programming Language :: Python :: 3.8
Classifier: Programming Language :: Python :: 3.9
Classifier: Programming Language :: Python :: 3.10
License-File: LICENSE.txt
Requires-Dist: scikit-image
Requires-Dist: opencv-python
Requires-Dist: pytesseract
Requires-Dist: numpy
Requires-Dist: PyAutoGUI
